retryCommand/__init__.py
retryCommand/__main__.py
retryCommand/cli.py
retrycommand-0.1.0.dist-info/licenses/LICENSE
retrycommand-0.1.0.dist-info/METADATA
retrycommand-0.1.0.dist-info/WHEEL
retrycommand-0.1.0.dist-info/entry_points.txt
retrycommand-0.1.0.dist-info/top_level.txt
retrycommand-0.1.0.dist-info/RECORD
