Metadata-Version: 2.4
Name: retryCommand
Version: 0.1.0
Summary: It is a Python library that allows you to retry executing a command multiple times until it succeeds or reaches the maximum number of retries. It provides options to customize the behavior of retries, such as setting a timeout for each execution and specifying the return codes that indicate success.
Author-email: kuankuan <2163826131@qq.com>
License-Expression: MulanPSL-2.0
Project-URL: Repository, https://github.com/kuankuan2007/retry-command
Project-URL: Issues, https://github.com/kuankuan2007/retry-command/issues
Keywords: cli,command line,retry,rich
Classifier: Natural Language :: English
Classifier: Development Status :: 4 - Beta
Classifier: Intended Audience :: Developers
Classifier: Programming Language :: Python :: 3
Classifier: Operating System :: MacOS
Classifier: Operating System :: POSIX :: Linux
Classifier: Operating System :: Microsoft :: Windows
Requires-Python: >=3.8
License-File: LICENSE
Requires-Dist: rich
Dynamic: license-file
